jupyter_protocol/__init__.py
jupyter_protocol/_version.py
jupyter_protocol/adapter.py
jupyter_protocol/jsonutil.py
jupyter_protocol/messages.py
jupyter_protocol/session.py
jupyter_protocol/sockets.py
jupyter_protocol/util.py
jupyter_protocol/win_interrupt.py
jupyter_protocol/tests/__init__.py
jupyter_protocol/tests/signalkernel.py
jupyter_protocol/tests/test_adapter.py
jupyter_protocol/tests/test_jsonutil.py
jupyter_protocol/tests/test_messages.py
jupyter_protocol/tests/test_public_api.py
jupyter_protocol/tests/test_session.py
jupyter_protocol/tests/test_sockets.py
jupyter_protocol/tests/utils.py
jupyter_protocol-0.2.0.dist-info/METADATA
jupyter_protocol-0.2.0.dist-info/RECORD
jupyter_protocol-0.2.0.dist-info/WHEEL
jupyter_protocol-0.2.0.dist-info/top_level.txt
