Metadata-Version: 2.1
Name: jupyter-protocol
Version: 0.2.0
Summary: Jupyter protocol implementation
Home-page: https://jupyter.org
Author: Jupyter Development Team
Author-email: jupyter@googlegroups.com
License: BSD
Platform: UNKNOWN
Classifier: Intended Audience :: Developers
Classifier: Intended Audience :: System Administrators
Classifier: Intended Audience :: Science/Research
Classifier: License :: OSI Approved :: BSD License
Classifier: Programming Language :: Python
Classifier: Programming Language :: Python :: 3
Requires-Python: >=3.5
Provides-Extra: test
Requires-Dist: traitlets
Requires-Dist: jupyter-core
Requires-Dist: pyzmq (>=13)
Requires-Dist: python-dateutil (>=2.1)
Provides-Extra: test
Requires-Dist: ipykernel; extra == 'test'
Requires-Dist: ipython; extra == 'test'
Requires-Dist: mock; extra == 'test'
Requires-Dist: pytest; extra == 'test'
